Metadata-Version: 1.1
Name: torch-sparse-old
Version: 0.4.4.0
Summary: PyTorch Extension Library of Optimized Autograd Sparse Matrix Operations
Home-page: https://github.com/rusty1s/pytorch_sparse
Author: Matthias Fey
Author-email: matthias.fey@tu-dortmund.de
License: UNKNOWN
Download-URL: https://github.com/rusty1s/pytorch_sparse/archive/0.4.4.0.tar.gz
Keywords: pytorch,sparse,sparse-matrices,autograd
Platform: UNKNOWN
